LICENSE.txt
MANIFEST.in
README.md
install.json
jupyter_msal_widget.json
package.json
pyproject.toml
pytest.ini
setup.cfg
setup.py
tsconfig.json
webpack.config.js
css/widget.css
docs/Makefile
docs/environment.yml
docs/make.bat
docs/source/conf.py
docs/source/develop-install.rst
docs/source/index.rst
docs/source/installing.rst
docs/source/introduction.rst
docs/source/_static/embed-bundle.js
docs/source/_static/embed-bundle.js.LICENSE.txt
docs/source/_static/embed-bundle.js.map
docs/source/_static/helper.js
docs/source/examples/index.rst
docs/source/examples/introduction.nblink
examples/introduction.ipynb
examples/.ipynb_checkpoints/Example-checkpoint.ipynb
examples/.ipynb_checkpoints/introduction-checkpoint.ipynb
jupyter_msal_widget/__init__.py
jupyter_msal_widget/_frontend.py
jupyter_msal_widget/_version.py
jupyter_msal_widget/widget.py
jupyter_msal_widget.egg-info/PKG-INFO
jupyter_msal_widget.egg-info/SOURCES.txt
jupyter_msal_widget.egg-info/dependency_links.txt
jupyter_msal_widget.egg-info/requires.txt
jupyter_msal_widget.egg-info/top_level.txt
jupyter_msal_widget/labextension/package.json
jupyter_msal_widget/labextension/static/367.8b628feb4c772fb8a4a7.js
jupyter_msal_widget/labextension/static/480.24f4cfca56a4bf5e1037.js
jupyter_msal_widget/labextension/static/486.962bd3a5e56e64b5c655.js
jupyter_msal_widget/labextension/static/486.962bd3a5e56e64b5c655.js.LICENSE.txt
jupyter_msal_widget/labextension/static/568.6f367ce574757cb27b1c.js
jupyter_msal_widget/labextension/static/624.70b378b818869c83679c.js
jupyter_msal_widget/labextension/static/624.70b378b818869c83679c.js.LICENSE.txt
jupyter_msal_widget/labextension/static/882.3c4a38f4ab5dc3a284cf.js
jupyter_msal_widget/labextension/static/882.3c4a38f4ab5dc3a284cf.js.LICENSE.txt
jupyter_msal_widget/labextension/static/remoteEntry.a640b3bf93dbf122f210.js
jupyter_msal_widget/labextension/static/style.js
jupyter_msal_widget/labextension/static/third-party-licenses.json
jupyter_msal_widget/nbextension/extension.js
jupyter_msal_widget/nbextension/index.js
jupyter_msal_widget/nbextension/index.js.LICENSE.txt
jupyter_msal_widget/nbextension/index.js.map
jupyter_msal_widget/tests/__init__.py
jupyter_msal_widget/tests/conftest.py
