Metadata-Version: 2.1
Name: jupyter-msal-widget
Version: 0.1.4
Summary: A Custom Jupyter Widget Library
Home-page: https://github.com/jupyter_msal_widget
Author: Felipe Oucharski
Author-email: felipe.oucharski@gmail.com
License: BSD
Keywords: Jupyter,Widgets,IPython
Platform: Linux
Platform: Mac OS X
Platform: Windows
Classifier: Intended Audience :: Developers
Classifier: Intended Audience :: Science/Research
Classifier: License :: OSI Approved :: BSD License
Classifier: Programming Language :: Python
Classifier: Programming Language :: Python :: 3
Classifier: Programming Language :: Python :: 3.4
Classifier: Programming Language :: Python :: 3.5
Classifier: Programming Language :: Python :: 3.6
Classifier: Programming Language :: Python :: 3.7
Classifier: Framework :: Jupyter
Requires-Python: >=3.6
Provides-Extra: test
Provides-Extra: examples
Provides-Extra: docs
License-File: LICENSE.txt
